mcdrtelegram/Telegram.py
mcdrtelegram/__init__.py
mcdrtelegram-0.4.1.dist-info/WHEEL
mcdrtelegram-0.4.1.dist-info/METADATA
mcdrtelegram-0.4.1.dist-info/RECORD
